aio_marantz_avr/__init__.py
aio_marantz_avr/avr.py
aio_marantz_avr/cli.py
aio_marantz_avr/enums.py
aio_marantz_avr-0.1.0.dist-info/AUTHORS.rst
aio_marantz_avr-0.1.0.dist-info/LICENSE
aio_marantz_avr-0.1.0.dist-info/METADATA
aio_marantz_avr-0.1.0.dist-info/WHEEL
aio_marantz_avr-0.1.0.dist-info/entry_points.txt
aio_marantz_avr-0.1.0.dist-info/top_level.txt
aio_marantz_avr-0.1.0.dist-info/RECORD
