Metadata-Version: 2.1
Name: aio-marantz-avr
Version: 0.1.0
Summary: AsyncIO access to Marantz AVRs.
Home-page: https://github.com/silvester747/aio_marantz_avr
Author: Rob van der Most
Author-email: silvester747@gmail.com
License: MIT license
Keywords: aio_marantz_avr
Platform: UNKNOWN
Classifier: Development Status :: 2 - Pre-Alpha
Classifier: Intended Audience :: Developers
Classifier: License :: OSI Approved :: MIT License
Classifier: Natural Language :: English
Classifier: Programming Language :: Python :: 3
Classifier: Programming Language :: Python :: 3.5
Classifier: Programming Language :: Python :: 3.6
Classifier: Programming Language :: Python :: 3.7
Classifier: Programming Language :: Python :: 3.8
Requires-Python: >=3.5
Requires-Dist: telnetlib3 (==1.0.2)
